ultima_scraper_renamer/__init__.py
ultima_scraper_renamer/py.typed
ultima_scraper_renamer/reformat.py
ultima_scraper_renamer/renamer.py
ultima_scraper_renamer-1.1.72.dist-info/METADATA
ultima_scraper_renamer-1.1.72.dist-info/WHEEL
ultima_scraper_renamer-1.1.72.dist-info/RECORD
