Metadata-Version: 2.1
Name: ultima-scraper-renamer
Version: 1.1.72
Summary: 
Author: UltimaHoarder
Author-email: 1285176+UltimaHoarder@users.noreply.github.com
Requires-Python: >=3.10,<4
Classifier: Programming Language :: Python :: 3
Classifier: Programming Language :: Python :: 3.10
Classifier: Programming Language :: Python :: 3.11
Classifier: Programming Language :: Python :: 3.12
Requires-Dist: orjson (>=3.8.3,<4.0.0)
Requires-Dist: tqdm (>=4.64.1,<5.0.0)
Requires-Dist: ultima-scraper-api (>=2.0.0,<3.0.0)
Requires-Dist: ultima-scraper-collection (>=2.0.0,<3.0.0)
